rosbag_to_dataframe/__init__.py
rosbag_to_dataframe/extractor.py
rosbag_to_dataframe-0.2.1.dist-info/LICENSE
rosbag_to_dataframe-0.2.1.dist-info/METADATA
rosbag_to_dataframe-0.2.1.dist-info/WHEEL
rosbag_to_dataframe-0.2.1.dist-info/top_level.txt
rosbag_to_dataframe-0.2.1.dist-info/RECORD
