Metadata-Version: 2.1
Name: rosbag-to-dataframe
Version: 0.2.1
Summary: A package to extract data from ROS2 bag files into pandas DataFrames.
Home-page: UNKNOWN
Author: Abhay Chaudhary
License: UNKNOWN
Platform: UNKNOWN
License-File: LICENSE
Requires-Dist: pandas
Requires-Dist: numpy
Requires-Dist: rosbag2-py
